{"nm":"Button-1","ddd":0,"h":65,"w":270,"meta":{"g":"@lottiefiles/toolkit-js 0.63.1"},"layers":[{"ty":4,"nm":"Shape Layer 3","sr":1,"st":0,"op":125,"ip":0,"ln":"356","hasMask":false,"ao":0,"ks":{"a":{"a":0,"k":[3.446,4.594,0]},"s":{"a":1,"k":[{"s":[34,0,100],"i":{"x":[0.667,0.667,0.667],"y":[1,1,1]},"o":{"x":[0.333,0.333,0.333],"y":[0,0,0]},"t":45},{"s":[50,50,100],"i":{"x":[0.99,0.99,0.99],"y":[1,1,0.994]},"o":{"x":[0.01,0.01,0.01],"y":[0,0,0.006]},"t":61.999}]},"p":{"a":0,"k":[11.971,12.547,0]},"r":{"a":0,"k":0},"o":{"a":0,"k":100}},"shapes":[{"ty":"gr","nm":"Shape 1","it":[{"ty":"sh","nm":"Path 1","d":1,"ks":{"a":0,"k":{"c":true,"i":[[6.625,0.125],[0,0],[0,0],[4.125,3.688]],"o":[[2.062,8.75],[0,0],[0,0],[-4.125,-3.688]],"v":[[-11.438,-13.25],[-4.375,4.812],[11.438,4.812],[16.625,-10.875]]}}},{"ty":"st","nm":"Stroke 1","lc":1,"lj":1,"ml":4,"o":{"a":0,"k":100},"w":{"a":0,"k":1.2},"c":{"a":0,"k":[1,1,1]}},{"ty":"fl","nm":"Fill 1","c":{"a":0,"k":[1,1,1]},"r":1,"o":{"a":0,"k":100}},{"ty":"tr","a":{"a":0,"k":[0,0]},"s":{"a":0,"k":[100,100]},"p":{"a":0,"k":[0,0]},"r":{"a":0,"k":0},"o":{"a":0,"k":100}}]}],"ind":1,"parent":2},{"ty":4,"nm":"Layer 1 Outlines","sr":1,"st":0,"op":125,"ip":0,"ln":"355","hasMask":false,"ao":0,"ks":{"a":{"a":0,"k":[1.5,19,0]},"s":{"a":0,"k":[200,200,100]},"p":{"a":1,"k":[{"o":{"x":0.192,"y":0},"i":{"x":0.596,"y":0.997},"s":[-40,50,0],"t":25},{"o":{"x":0.167,"y":0.167},"i":{"x":0.596,"y":0.596},"s":[117.504,50,0],"t":40},{"o":{"x":0.167,"y":0},"i":{"x":0.794,"y":0.996},"s":[117.504,50,0],"t":69.999},{"s":[294.031,50,0],"t":90.999}]},"r":{"a":1,"k":[{"o":{"x":0.333,"y":0},"i":{"x":0.667,"y":1},"s":[0],"t":69.999},{"o":{"x":0.333,"y":0},"i":{"x":0.667,"y":1},"s":[-13],"t":74.999},{"s":[0],"t":90.999}]},"o":{"a":0,"k":100}},"shapes":[{"ty":"gr","nm":"Group 1","it":[{"ty":"sh","nm":"Path 1","d":1,"ks":{"a":0,"k":{"c":false,"i":[[0,0],[0,0],[0.051,0.139],[0.444,0.326],[0.55,0.038],[0.227,0]],"o":[[0,0],[-0.042,-0.141],[-0.202,-0.512],[-0.445,-0.325],[-0.103,-0.008],[0,0]],"v":[[-5.658,-3.391],[-5.669,-3.428],[-5.809,-3.848],[-6.798,-5.131],[-8.32,-5.688],[-8.764,-5.695]]}}},{"ty":"sh","nm":"Path 2","d":1,"ks":{"a":0,"k":{"c":true,"i":[[0,0],[0,0],[-0.297,-0.362],[-0.383,-0.153],[-1.026,0],[0,0],[-0.434,0.173],[-0.261,0.32],[-0.31,0.978],[0,0],[0,0],[0,0],[0.064,0.387],[0.232,0.317],[0.35,0.178],[0.393,0]],"o":[[0,0],[0.309,0.978],[0.26,0.32],[0.435,0.173],[0,0],[1.026,0],[0.384,-0.153],[0.296,-0.362],[0,0],[0,0],[0,0],[0.118,-0.374],[-0.063,-0.387],[-0.232,-0.317],[-0.35,-0.177],[0,0]],"v":[[-5.658,-3.391],[-3.648,2.973],[-2.887,4.803],[-1.906,5.523],[0.068,5.695],[3.923,5.695],[5.895,5.523],[6.878,4.803],[7.637,2.973],[8.046,1.678],[8.286,0.911],[8.617,-0.139],[8.699,-1.298],[8.249,-2.368],[7.363,-3.12],[6.234,-3.391]]}}},{"ty":"st","nm":"Stroke 1","lc":2,"lj":2,"ml":4,"o":{"a":0,"k":100},"w":{"a":0,"k":1.2},"c":{"a":0,"k":[1,1,1]}},{"ty":"tr","a":{"a":0,"k":[0,0]},"s":{"a":0,"k":[100,100]},"p":{"a":0,"k":[10.263,7.196]},"r":{"a":0,"k":0},"o":{"a":0,"k":100}}]},{"ty":"gr","nm":"Group 2","it":[{"ty":"sh","nm":"Path 1","d":1,"ks":{"a":0,"k":{"c":true,"i":[[-0.939,0],[0,0.939],[0.939,0],[0,-0.939]],"o":[[0.939,0],[0,-0.939],[-0.939,0],[0,0.939]],"v":[[0,1.701],[1.701,0],[0,-1.701],[-1.701,0]]}}},{"ty":"st","nm":"Stroke 1","lc":2,"lj":2,"ml":4,"o":{"a":0,"k":100},"w":{"a":0,"k":1.2},"c":{"a":0,"k":[1,1,1]}},{"ty":"tr","a":{"a":0,"k":[0,0]},"s":{"a":0,"k":[100,100]},"p":{"a":0,"k":[15.96,17.299]},"r":{"a":0,"k":0},"o":{"a":0,"k":100}}]},{"ty":"gr","nm":"Group 3","it":[{"ty":"sh","nm":"Path 1","d":1,"ks":{"a":0,"k":{"c":true,"i":[[-0.939,0],[0,0.939],[0.939,0],[0,-0.939]],"o":[[0.939,0],[0,-0.939],[-0.939,0],[0,0.939]],"v":[[0,1.701],[1.701,0],[0,-1.701],[-1.701,0]]}}},{"ty":"st","nm":"Stroke 1","lc":2,"lj":2,"ml":4,"o":{"a":0,"k":100},"w":{"a":0,"k":1.2},"c":{"a":0,"k":[1,1,1]}},{"ty":"tr","a":{"a":0,"k":[0,0]},"s":{"a":0,"k":[100,100]},"p":{"a":0,"k":[8.549,17.299]},"r":{"a":0,"k":0},"o":{"a":0,"k":100}}]}],"ind":2},{"ty":5,"nm":"ADD TO CART 5","sr":1,"st":-74,"op":57,"ip":-28,"ln":"358","hasMask":false,"ao":0,"ks":{"a":{"a":0,"k":[0,0]},"s":{"a":0,"k":[110,110,100]},"p":{"a":1,"k":[{"o":{"x":0.333,"y":0},"i":{"x":0.667,"y":1},"s":[135.336,41.571,0],"t":13.999},{"s":[135.336,-2.263,0],"t":26.999}]},"r":{"a":0,"k":0},"o":{"a":0,"k":100}},"t":{"m":{"a":{"a":0,"k":[0,0]},"g":1},"p":{"f":{"a":0,"k":0},"l":{"a":0,"k":0},"r":{"a":0,"k":0},"a":{"a":0,"k":0},"p":{"a":0,"k":0}},"a":[],"d":{"k":[{"s":{"f":"Inter-Regular","s":24,"t":"ADD TO CART","fc":[1,1,1],"lh":21,"tr":-3,"j":2,"ca":0},"t":0}]}},"ind":3},{"ty":5,"nm":"ADD TO CART 4","sr":1,"st":-2,"op":129,"ip":86,"ln":"357","hasMask":false,"ao":0,"ks":{"a":{"a":0,"k":[0,0]},"s":{"a":0,"k":[110,110,100]},"p":{"a":1,"k":[{"o":{"x":0.333,"y":0},"i":{"x":0.501,"y":1},"s":[135.336,84.737,0],"t":85.999},{"s":[135.336,41.571,0],"t":98.999}]},"r":{"a":0,"k":0},"o":{"a":0,"k":100}},"t":{"m":{"a":{"a":0,"k":[0,0]},"g":1},"p":{"f":{"a":0,"k":0},"l":{"a":0,"k":0},"r":{"a":0,"k":0},"a":{"a":0,"k":0},"p":{"a":0,"k":0}},"a":[],"d":{"k":[{"s":{"f":"Inter-Regular","s":24,"t":"ADD TO CART","fc":[1,1,1],"lh":21,"tr":-3,"j":2,"ca":0},"t":0}]}},"ind":4},{"ty":4,"nm":"Shape Layer 4","sr":1,"st":0,"op":125,"ip":0,"ln":"352","hasMask":false,"ao":0,"ks":{"a":{"a":0,"k":[0,0]},"s":{"a":0,"k":[100,100]},"p":{"a":0,"k":[135,32.5]},"r":{"a":0,"k":0},"o":{"a":0,"k":100}},"shapes":[{"ty":"gr","nm":"Rectangle 1","it":[{"ty":"rc","nm":"Rectangle Path 1","d":1,"p":{"a":0,"k":[0,0]},"r":{"a":0,"k":8},"s":{"a":0,"k":[270.597,65.467]}},{"ty":"st","nm":"Stroke 1","lc":1,"lj":1,"ml":4,"o":{"a":0,"k":100},"w":{"a":0,"k":0},"c":{"a":0,"k":[1,1,1]}},{"ty":"fl","nm":"Fill 1","c":{"a":0,"k":[0,0,0]},"r":1,"o":{"a":0,"k":100}},{"ty":"tr","a":{"a":0,"k":[0,0]},"s":{"a":0,"k":[100,100]},"p":{"a":0,"k":[-0.23,0.179]},"r":{"a":0,"k":0},"o":{"a":0,"k":100}}]}],"ind":5}],"v":"5.7.0","fr":29.97,"op":125.68064516129031,"ip":0,"fonts":{"list":[{"ascent":null,"fClass":"","fFamily":"Inter","fStyle":"Regular","fName":"Inter-Regular","fPath":"","fWeight":"","origin":0}]},"assets":[]}